{"cameraMode":{"drawMode":0,"name":"Shaded","section":"Shading Mode"},"sceneLighting":false,"audioPlay":false,"sceneViewState":{"m_AlwaysRefresh":false,"showFog":true,"showSkybox":true,"showFlares":true,"showImageEffects":true,"showParticleSystems":true,"showVisualEffectGraphs":true,"m_FxEnabled":true},"in2DMode":false,"pivot":{"x":-5.88089656829834,"y":12.48635196685791,"z":-26.599010467529298},"rotation":{"x":0.11258430033922196,"y":0.09968522191047669,"z":-0.011355055496096611,"w":0.9885672330856323},"size":39.7303581237793,"orthographic":false}