{"cameraMode":{"drawMode":0,"name":"Shaded","section":"Shading Mode"},"sceneLighting":false,"audioPlay":false,"sceneViewState":{"m_AlwaysRefresh":false,"showFog":true,"showSkybox":true,"showFlares":true,"showImageEffects":true,"showParticleSystems":true,"showVisualEffectGraphs":true,"m_FxEnabled":true},"in2DMode":false,"pivot":{"x":40.89411163330078,"y":-12.726444244384766,"z":76.58486938476563},"rotation":{"x":-0.12891770899295808,"y":-0.558201253414154,"z":0.08829928189516068,"w":-0.8148830533027649},"size":58.54025650024414,"orthographic":false}